comp_df_syren/__init__.py
comp_df_syren-0.2.1.dist-info/LICENCE.txt
comp_df_syren-0.2.1.dist-info/METADATA
comp_df_syren-0.2.1.dist-info/WHEEL
comp_df_syren-0.2.1.dist-info/top_level.txt
comp_df_syren-0.2.1.dist-info/RECORD
