Metadata-Version: 2.1
Name: comp-df-syren
Version: 0.2.1
Summary: DATAFRAMES COMPARISON
Home-page: UNKNOWN
Author: seshkalyan
Author-email: dseshkalyan@gmail.com
License: SYREN CLOUD TECHNOLOGIES
Platform: UNKNOWN
License-File: LICENCE.txt
